[
  {
    "index": 118,
    "brand": "Franklin",
    "name": "FS Tour Tempo (14mm)",
    "image_url": "https://cdn11.bigcommerce.com/s-t7feygfjjq/images/stencil/1280x1280/products/5326/29636/aaa15480e5a958d1b0eeface461966fc4a50f902f240186e9d3add65814a0d88__49866.1710524434.jpg?c=1"
  },
  {
    "index": 119,
    "brand": "Franklin",
    "name": "FS Tour Tempo (16mm)",
    "image_url": "https://cdn11.bigcommerce.com/s-tl5mxjzfsl/images/stencil/1000x1000/products/5201/27773/FRKL204_FranklinFSTourTempo__16mm_Blu_1_1000__08414.1701892098.jpg?c=1"
  },
  {
    "index": 120,
    "brand": "Friday",
    "name": "Aura E",
    "image_url": "https://fridaypickle.com/cdn/shop/files/lunar-aura-hero-color_4e498238-7ff2-4767-86e1-6650a5e5579f.jpg?v=1772700668"
  },
  {
    "index": 121,
    "brand": "Friday",
    "name": "Aura H",
    "image_url": "https://fridaypickle.com/cdn/shop/files/lunar-aura-hero-color_4e498238-7ff2-4767-86e1-6650a5e5579f.jpg?v=1772700668"
  },
  {
    "index": 122,
    "brand": "Friday",
    "name": "Aura Pro E",
    "image_url": "https://fridaypickle.com/cdn/shop/files/lunar-aura-pro-hero-color_4c7c5c75-3882-4a96-a969-ff415d5676c7.jpg?v=1772708863"
  },
  {
    "index": 123,
    "brand": "Friday",
    "name": "Aura W",
    "image_url": "https://fridaypickle.com/cdn/shop/files/lunar-aura-hero-color_4e498238-7ff2-4767-86e1-6650a5e5579f.jpg?v=1772700668"
  },
  {
    "index": 132,
    "brand": "Gearbox",
    "name": "CX14H Ultimate Power",
    "image_url": "https://gearboxsports.com/cdn/shop/products/CX14H_Ultimate_Power_2-min.jpg?v=1677689776"
  },
  {
    "index": 133,
    "brand": "Gearbox",
    "name": "GBX Power Elongated",
    "image_url": "https://www.pickleballgalaxy.com/mm5/graphics/00000001/6/gearbox-gbx-power-elongated-16.jpg"
  },
  {
    "index": 134,
    "brand": "Gearbox",
    "name": "GBX Power Hybrid",
    "image_url": "https://www.pickleballgalaxy.com/mm5/graphics/00000001/6/gearbox-gbx-power-hybrid-16.jpg"
  },
  {
    "index": 161,
    "brand": "Head",
    "name": "Radical Pro 15",
    "image_url": "https://www.holabirdsports.com/cdn/shop/files/360776_1.jpg?v=1771438081"
  },
  {
    "index": 162,
    "brand": "Head",
    "name": "Radical Pro EX 15",
    "image_url": "https://www.holabirdsports.com/cdn/shop/files/360777_1.jpg?v=1771438081"
  },
  {
    "index": 163,
    "brand": "Head",
    "name": "Tour Radical Raw EX",
    "image_url": "https://cdn11.bigcommerce.com/s-5nfcahck7c/images/stencil/608x608/products/3201/13313/radical-tour-ex-raw-2024__95054.1718305050.jpg?c=2"
  },
  {
    "index": 211,
    "brand": "JOOLA",
    "name": "Mod TA-15 (16mm)",
    "image_url": "https://dac8r2vkxfv8c.cloudfront.net/images/products/8687-08-24-joola-mod-ta-15-16mm-carbon-fiber-pickleball-paddle-38129-4_l.jpg"
  },
  {
    "index": 227,
    "brand": "JOOLA",
    "name": "Hyperion 3S (16mm)",
    "image_url": "https://joola.com/cdn/shop/files/17070-BJ-Hyperion3S-16mm-WBG-01.jpg?v=1724073948"
  },
  {
    "index": 228,
    "brand": "JOOLA",
    "name": "Perseus 3S (16mm)",
    "image_url": "https://joola.com/cdn/shop/files/17063-Perseus_3S-16mm-WBG-01.jpg?v=1724075177"
  },
  {
    "index": 238,
    "brand": "Maverix",
    "name": "Havik-15 All-Court",
    "image_url": "https://www.maverixpickleball.com/cdn/shop/files/1.jpg?v=1717691673"
  },
  {
    "index": 239,
    "brand": "Maverix",
    "name": "Havik-15 Pro",
    "image_url": "https://www.maverixpickleball.com/cdn/shop/files/Mainpicture.jpg?v=1717691573"
  },
  {
    "index": 245,
    "brand": "Paddletek",
    "name": "Bantam ALW-C 12.7",
    "image_url": "https://www.paddletek.com/cdn/shop/files/Paddletek_Bantam_ALW-C_Ocean_12.7_Front.png?v=1773083022&width=2048"
  },
  {
    "index": 246,
    "brand": "Paddletek",
    "name": "Bantam ALW-C 14.3",
    "image_url": "https://www.paddletek.com/cdn/shop/files/Paddletek_Bantam_ALW-C_Ocean_12.7_Front.png?v=1773083022&width=2048"
  },
  {
    "index": 247,
    "brand": "Paddletek",
    "name": "Bantam ESQ-C 12.7",
    "image_url": "https://www.paddletek.com/cdn/shop/files/Paddletek_Bantam_ESQ-C_Ocean_12.7_Front.png?v=1763067939&width=2048"
  },
  {
    "index": 248,
    "brand": "Paddletek",
    "name": "Bantam ESQ-C 14.3",
    "image_url": "https://www.paddletek.com/cdn/shop/files/Paddletek_Bantam_ESQ-C_Ocean_12.7_Front.png?v=1763067939&width=2048"
  }
]
